shhistory.py
shhistory-0.1.9.dist-info/LICENSE
shhistory-0.1.9.dist-info/METADATA
shhistory-0.1.9.dist-info/WHEEL
shhistory-0.1.9.dist-info/top_level.txt
shhistory-0.1.9.dist-info/RECORD
