Metadata-Version: 2.1
Name: shhistory
Version: 0.1.9
Summary: Simple Python library to return your shell history or dump to a nicely formatted JSON file.
Home-page: https://github.com/battleoverflow/shhistory
Author: battleoverflow
Classifier: Programming Language :: Python :: 3
Classifier: License :: OSI Approved :: BSD License
Classifier: Operating System :: OS Independent
Requires-Python: >=3.6
License-File: LICENSE
